{
  "count": 10,
  "results": [
    {
      "instance_id": "django__django-13128",
      "analysis_time": 0.0,
      "scope": {},
      "metrics": {},
      "errors": [
        "Clone failed: Clone failed: Git clone failed: fatal: 'django/django' \uc800\uc7a5\uc18c\uac00 \uc5c6\uc2b5\ub2c8\ub2e4\n"
      ],
      "repo_name": "django_django",
      "base_commit": "2d67222472f80f251607ae1b720527afceba06ad"
    },
    {
      "instance_id": "django__django-13158",
      "analysis_time": 0.0,
      "scope": {},
      "metrics": {},
      "errors": [
        "Clone failed: Clone failed: Git clone failed: fatal: 'django/django' \uc800\uc7a5\uc18c\uac00 \uc5c6\uc2b5\ub2c8\ub2e4\n"
      ],
      "repo_name": "django_django",
      "base_commit": "7af8f4127397279d19ef7c7899e93018274e2f9b"
    },
    {
      "instance_id": "django__django-13195",
      "analysis_time": 0.0,
      "scope": {},
      "metrics": {},
      "errors": [
        "Clone failed: Clone failed: Git clone failed: fatal: 'django/django' \uc800\uc7a5\uc18c\uac00 \uc5c6\uc2b5\ub2c8\ub2e4\n"
      ],
      "repo_name": "django_django",
      "base_commit": "156a2138db20abc89933121e4ff2ee2ce56a173a"
    },
    {
      "instance_id": "django__django-13212",
      "analysis_time": 0.0,
      "scope": {},
      "metrics": {},
      "errors": [
        "Clone failed: Clone failed: Git clone failed: fatal: 'django/django' \uc800\uc7a5\uc18c\uac00 \uc5c6\uc2b5\ub2c8\ub2e4\n"
      ],
      "repo_name": "django_django",
      "base_commit": "f4e93919e4608cfc50849a1f764fd856e0917401"
    },
    {
      "instance_id": "django__django-13279",
      "analysis_time": 0.0,
      "scope": {},
      "metrics": {},
      "errors": [
        "Clone failed: Clone failed: Git clone failed: fatal: 'django/django' \uc800\uc7a5\uc18c\uac00 \uc5c6\uc2b5\ub2c8\ub2e4\n"
      ],
      "repo_name": "django_django",
      "base_commit": "6e9c5ee88fc948e05b4a7d9f82a8861ed2b0343d"
    },
    {
      "instance_id": "django__django-13297",
      "analysis_time": 0.0,
      "scope": {},
      "metrics": {},
      "errors": [
        "Clone failed: Clone failed: Git clone failed: fatal: 'django/django' \uc800\uc7a5\uc18c\uac00 \uc5c6\uc2b5\ub2c8\ub2e4\n"
      ],
      "repo_name": "django_django",
      "base_commit": "8954f255bbf5f4ee997fd6de62cb50fc9b5dd697"
    },
    {
      "instance_id": "django__django-13315",
      "analysis_time": 0.0,
      "scope": {},
      "metrics": {},
      "errors": [
        "Clone failed: Clone failed: Git clone failed: fatal: 'django/django' \uc800\uc7a5\uc18c\uac00 \uc5c6\uc2b5\ub2c8\ub2e4\n"
      ],
      "repo_name": "django_django",
      "base_commit": "36bc47069ce071e80c8129500de3b8664d2058a7"
    },
    {
      "instance_id": "django__django-13343",
      "analysis_time": 0.0,
      "scope": {},
      "metrics": {},
      "errors": [
        "Clone failed: Clone failed: Git clone failed: fatal: 'django/django' \uc800\uc7a5\uc18c\uac00 \uc5c6\uc2b5\ub2c8\ub2e4\n"
      ],
      "repo_name": "django_django",
      "base_commit": "ece18207cbb64dd89014e279ac636a6c9829828e"
    },
    {
      "instance_id": "django__django-13344",
      "analysis_time": 0.0,
      "scope": {},
      "metrics": {},
      "errors": [
        "Clone failed: Clone failed: Git clone failed: fatal: 'django/django' \uc800\uc7a5\uc18c\uac00 \uc5c6\uc2b5\ub2c8\ub2e4\n"
      ],
      "repo_name": "django_django",
      "base_commit": "e39e727ded673e74016b5d3658d23cbe20234d11"
    },
    {
      "instance_id": "django__django-13346",
      "analysis_time": 0.0,
      "scope": {},
      "metrics": {},
      "errors": [
        "Clone failed: Clone failed: Git clone failed: fatal: 'django/django' \uc800\uc7a5\uc18c\uac00 \uc5c6\uc2b5\ub2c8\ub2e4\n"
      ],
      "repo_name": "django_django",
      "base_commit": "9c92924cd5d164701e2514e1c2d6574126bd7cc2"
    }
  ],
  "errors": [
    {
      "instance_id": "django__django-13128",
      "errors": [
        "Clone failed: Clone failed: Git clone failed: fatal: 'django/django' \uc800\uc7a5\uc18c\uac00 \uc5c6\uc2b5\ub2c8\ub2e4\n"
      ]
    },
    {
      "instance_id": "django__django-13158",
      "errors": [
        "Clone failed: Clone failed: Git clone failed: fatal: 'django/django' \uc800\uc7a5\uc18c\uac00 \uc5c6\uc2b5\ub2c8\ub2e4\n"
      ]
    },
    {
      "instance_id": "django__django-13195",
      "errors": [
        "Clone failed: Clone failed: Git clone failed: fatal: 'django/django' \uc800\uc7a5\uc18c\uac00 \uc5c6\uc2b5\ub2c8\ub2e4\n"
      ]
    },
    {
      "instance_id": "django__django-13212",
      "errors": [
        "Clone failed: Clone failed: Git clone failed: fatal: 'django/django' \uc800\uc7a5\uc18c\uac00 \uc5c6\uc2b5\ub2c8\ub2e4\n"
      ]
    },
    {
      "instance_id": "django__django-13279",
      "errors": [
        "Clone failed: Clone failed: Git clone failed: fatal: 'django/django' \uc800\uc7a5\uc18c\uac00 \uc5c6\uc2b5\ub2c8\ub2e4\n"
      ]
    },
    {
      "instance_id": "django__django-13297",
      "errors": [
        "Clone failed: Clone failed: Git clone failed: fatal: 'django/django' \uc800\uc7a5\uc18c\uac00 \uc5c6\uc2b5\ub2c8\ub2e4\n"
      ]
    },
    {
      "instance_id": "django__django-13315",
      "errors": [
        "Clone failed: Clone failed: Git clone failed: fatal: 'django/django' \uc800\uc7a5\uc18c\uac00 \uc5c6\uc2b5\ub2c8\ub2e4\n"
      ]
    },
    {
      "instance_id": "django__django-13343",
      "errors": [
        "Clone failed: Clone failed: Git clone failed: fatal: 'django/django' \uc800\uc7a5\uc18c\uac00 \uc5c6\uc2b5\ub2c8\ub2e4\n"
      ]
    },
    {
      "instance_id": "django__django-13344",
      "errors": [
        "Clone failed: Clone failed: Git clone failed: fatal: 'django/django' \uc800\uc7a5\uc18c\uac00 \uc5c6\uc2b5\ub2c8\ub2e4\n"
      ]
    },
    {
      "instance_id": "django__django-13346",
      "errors": [
        "Clone failed: Clone failed: Git clone failed: fatal: 'django/django' \uc800\uc7a5\uc18c\uac00 \uc5c6\uc2b5\ub2c8\ub2e4\n"
      ]
    }
  ]
}